cn_workday/__init__.py
cn_workday/utils.py
cn_workday/data/2017.csv
cn_workday/data/2018.csv
cn_workday/data/2019.csv
cn_workday/data/2020.csv
cn_workday-2020.1.27.1.dist-info/LICENSE
cn_workday-2020.1.27.1.dist-info/METADATA
cn_workday-2020.1.27.1.dist-info/WHEEL
cn_workday-2020.1.27.1.dist-info/top_level.txt
cn_workday-2020.1.27.1.dist-info/RECORD
