Metadata-Version: 2.1
Name: cn-workday
Version: 2020.1.27.1
Summary: Workday detection for China
Home-page: https://github.com/JokerQyou/cn_workday
Author: Joker Qyou
License: UNKNOWN
Platform: UNKNOWN
Classifier: Development Status :: 4 - Beta
Classifier: License :: OSI Approved :: MIT License
Requires-Dist: pytz (>=2019.3)
